mcp_server_snowflake/__init__.py
mcp_server_snowflake/main.py
mcp_server_snowflake/utils/__init__.py
mcp_server_snowflake/utils/snowflake_conn.py
mcp_server_snowflake/utils/template.py
mcp_snowflake-0.2.0.dist-info/METADATA
mcp_snowflake-0.2.0.dist-info/WHEEL
mcp_snowflake-0.2.0.dist-info/entry_points.txt
mcp_snowflake-0.2.0.dist-info/licenses/LICENSE
mcp_snowflake-0.2.0.dist-info/RECORD
