Metadata-Version: 2.4
Name: mcp_snowflake
Version: 0.2.0
Summary: MCP server for performing read-only operations against Snowflake
Project-URL: Repository, https://github.com/dynamike/mcp-server-snowflake
Project-URL: Issues, https://github.com/dynamike/mcp-server-snowflake/issues
Author: MCP Server Team
License: MIT
License-File: LICENSE
Keywords: claude,database,mcp,snowflake,sql
Classifier: Development Status :: 4 - Beta
Classifier: Intended Audience :: Developers
Classifier: License :: OSI Approved :: MIT License
Classifier: Programming Language :: Python :: 3
Classifier: Programming Language :: Python :: 3.12
Classifier: Topic :: Database
Classifier: Topic :: Software Development :: Libraries :: Python Modules
Requires-Python: >=3.12
Requires-Dist: anyio>=3.7.1
Requires-Dist: cryptography>=41.0.0
Requires-Dist: mcp
Requires-Dist: pydantic>=2.4.2
Requires-Dist: python-dotenv>=1.0.0
Requires-Dist: snowflake-connector-python>=3.8.0
Requires-Dist: sqlglot>=11.5.5
Provides-Extra: dev
Requires-Dist: mypy>=1.6.0; extra == 'dev'
Requires-Dist: pytest>=7.4.0; extra == 'dev'
Requires-Dist: ruff>=0.1.0; extra == 'dev'
